odoo/addons/crm_phonecall_result/README.rst
odoo/addons/crm_phonecall_result/__init__.py
odoo/addons/crm_phonecall_result/__manifest__.py
odoo/addons/crm_phonecall_result/data/crm_phonecall_result_data.xml
odoo/addons/crm_phonecall_result/i18n/ca.po
odoo/addons/crm_phonecall_result/i18n/crm_phonecall_result.pot
odoo/addons/crm_phonecall_result/i18n/es.po
odoo/addons/crm_phonecall_result/i18n/it.po
odoo/addons/crm_phonecall_result/models/__init__.py
odoo/addons/crm_phonecall_result/models/crm_phonecall.py
odoo/addons/crm_phonecall_result/models/crm_phonecall_result.py
odoo/addons/crm_phonecall_result/readme/CONTRIBUTORS.md
odoo/addons/crm_phonecall_result/readme/DESCRIPTION.md
odoo/addons/crm_phonecall_result/readme/USAGE.md
odoo/addons/crm_phonecall_result/report/__init__.py
odoo/addons/crm_phonecall_result/report/crm_phonecall_report.py
odoo/addons/crm_phonecall_result/security/ir.model.access.csv
odoo/addons/crm_phonecall_result/static/description/icon.png
odoo/addons/crm_phonecall_result/static/description/index.html
odoo/addons/crm_phonecall_result/tests/__init__.py
odoo/addons/crm_phonecall_result/tests/test_crm_phonecall_result.py
odoo/addons/crm_phonecall_result/views/crm_phonecall_result_views.xml
odoo/addons/crm_phonecall_result/views/crm_phonecall_views.xml
odoo_addon_crm_phonecall_result-18.0.1.0.0.5.dist-info/METADATA
odoo_addon_crm_phonecall_result-18.0.1.0.0.5.dist-info/WHEEL
odoo_addon_crm_phonecall_result-18.0.1.0.0.5.dist-info/top_level.txt
odoo_addon_crm_phonecall_result-18.0.1.0.0.5.dist-info/RECORD
