Metadata-Version: 2.1
Name: odoo-addon-crm_phonecall_result
Version: 18.0.1.0.0.5
Requires-Python: >=3.10
Requires-Dist: odoo-addon-crm_phonecall==18.0.*
Requires-Dist: odoo==18.0.*
Summary: Adds phone call result tracking and reporting to CRM phonecalls
Home-page: https://github.com/OCA/crm
License: AGPL-3
Author: Odoo Community Association (OCA)
Author-email: support@odoo-community.org
Classifier: Programming Language :: Python
Classifier: Framework :: Odoo
Classifier: Framework :: Odoo :: 18.0
Classifier: License :: OSI Approved :: GNU Affero General Public License v3
